logpro/__init__.py
logpro/logpro.py
logpro-0.1.2.dist-info/LICENSE
logpro-0.1.2.dist-info/METADATA
logpro-0.1.2.dist-info/WHEEL
logpro-0.1.2.dist-info/top_level.txt
logpro-0.1.2.dist-info/RECORD
