Metadata-Version: 2.1
Name: logpro
Version: 0.1.2
Summary: A simple logger for python.
Author: Vidpic
License: MIT License
Project-URL: Repository, https://github.com/Vidpic/logpro
Project-URL: Issues, https://github.com/Vidpic/logpro/issues
Classifier: Programming Language :: Python :: 3
Classifier: Programming Language :: Python :: 3.9
Classifier: License :: OSI Approved :: MIT License
Requires-Python: >=3.9
License-File: LICENSE
Requires-Dist: colorlog
